PolibasePersonNotificationService/__init__.py
PolibasePersonNotificationService/__main__.py
PolibasePersonNotificationService/api.py
PolibasePersonNotificationService/const.py
PolibasePersonNotificationService/service.py
pih_plb_ntf-1.0.dist-info/METADATA
pih_plb_ntf-1.0.dist-info/WHEEL
pih_plb_ntf-1.0.dist-info/entry_points.txt
pih_plb_ntf-1.0.dist-info/top_level.txt
pih_plb_ntf-1.0.dist-info/RECORD
